jsdict/__init__.py
jsdict_py-1.0.1.dist-info/LICENSE
jsdict_py-1.0.1.dist-info/METADATA
jsdict_py-1.0.1.dist-info/WHEEL
jsdict_py-1.0.1.dist-info/top_level.txt
jsdict_py-1.0.1.dist-info/RECORD
