Metadata-Version: 2.1
Name: jsdict-py
Version: 1.0.1
Summary: Javascript-syle Dictionaries in Python
Home-page: https://github.com/zevaryx/jsdict
Author: zevaryx
Author-email: zevaryx@gmail.com
License: UNKNOWN
Platform: UNKNOWN
Classifier: Programming Language :: Python :: 3
Classifier: License :: OSI Approved :: GNU General Public License v3 (GPLv3)
Classifier: Operating System :: OS Independent
